batchrenamer/__init__.py
batchrenamer/__main__.py
batchrenamer/batchrenamer.py
batchrenamer/filehistory.py
test/__init__.py
test/test_batchrenamer.py
batchrenamer-1.3.0.dist-info/LICENSE
batchrenamer-1.3.0.dist-info/METADATA
batchrenamer-1.3.0.dist-info/WHEEL
batchrenamer-1.3.0.dist-info/top_level.txt
batchrenamer-1.3.0.dist-info/RECORD
