Metadata-Version: 2.1
Name: batchrenamer
Version: 1.3.0
Summary: Rename multiple files with the same rules
Home-page: https://github.com/spslater/batchrenamer
Author: Sean Slater
Author-email: seanslater@whatno.io
License: MIT License
Keywords: filesystem files rename batch
Platform: UNKNOWN
Classifier: Development Status :: 4 - Beta
Classifier: Programming Language :: Python :: 3
Classifier: Programming Language :: Python :: 3.9
Classifier: Operating System :: OS Independent
Classifier: License :: OSI Approved :: MIT License
Classifier: Topic :: Utilities
Classifier: Topic :: System :: Filesystems
Classifier: Environment :: Console
Requires-Python: >=3.9
License-File: LICENSE
